wbia_lca/_version.py
wbia_lca-4.0.2.dist-info/LICENSE
wbia_lca-4.0.2.dist-info/METADATA
wbia_lca-4.0.2.dist-info/WHEEL
wbia_lca-4.0.2.dist-info/top_level.txt
wbia_lca-4.0.2.dist-info/RECORD
