Metadata-Version: 2.1
Name: wbia-lca
Version: 4.0.2
Summary: Localized Clustering and Alternatives (LCA) - An algorithm for curating a graph of animal sightings
Home-page: https://github.com/WildbookOrg/wbia-plugin-lca
Author: Dr. Charles Stewart, Jason Parham, Wild Me Developers
Author-email: dev@wildme.org
License: Apache License 2.0
Project-URL: Bug Reports, https://github.com/WildbookOrg/wbia-plugin-lca/issues
Project-URL: Funding, https://www.wildme.org/donate/
Project-URL: Say Thanks!, https://community.wildbook.org
Project-URL: Source, https://github.com/WildbookOrg/wbia-plugin-lca
Keywords: wildbook,wildme,ibeis,ecological,wildlife,conservation,machine learning,ai,hotspotter,detection,classification,animal ID,re-id,re-identification,flukebook
Platform: UNKNOWN
Classifier: Development Status :: 5 - Production/Stable
Classifier: Environment :: Console
Classifier: Environment :: Web Environment
Classifier: Environment :: GPU
Classifier: Environment :: GPU :: NVIDIA CUDA :: 11.0
Classifier: Natural Language :: English
Classifier: License :: OSI Approved :: Apache Software License
Classifier: Intended Audience :: Developers
Classifier: Intended Audience :: Science/Research
Classifier: Operating System :: MacOS :: MacOS X
Classifier: Operating System :: Unix
Classifier: Topic :: Software Development :: Libraries :: Python Modules
Classifier: Topic :: Scientific/Engineering :: Artificial Intelligence
Classifier: Topic :: Utilities
Classifier: Programming Language :: Python :: 3
Classifier: Programming Language :: Python :: 3.6
Classifier: Programming Language :: Python :: 3.7
Classifier: Programming Language :: Python :: 3.8
Classifier: Programming Language :: Python :: 3 :: Only
Requires-Python: >=3.5, <4
License-File: LICENSE
Requires-Dist: matplotlib
Requires-Dist: networkx
Requires-Dist: numpy
Requires-Dist: scipy
Requires-Dist: Sphinx
Requires-Dist: sphinx-rtd-theme
Requires-Dist: wbia-utool
Requires-Dist: wildbook-ia
Provides-Extra: all
Requires-Dist: cmake ; extra == 'all'
Requires-Dist: ninja ; extra == 'all'
Requires-Dist: scikit-build ; extra == 'all'
Requires-Dist: setuptools ; extra == 'all'
Requires-Dist: setuptools-scm[toml] ; extra == 'all'
Requires-Dist: wheel ; extra == 'all'
Requires-Dist: matplotlib ; extra == 'all'
Requires-Dist: networkx ; extra == 'all'
Requires-Dist: numpy ; extra == 'all'
Requires-Dist: scipy ; extra == 'all'
Requires-Dist: Sphinx ; extra == 'all'
Requires-Dist: sphinx-rtd-theme ; extra == 'all'
Requires-Dist: wbia-utool ; extra == 'all'
Requires-Dist: wildbook-ia ; extra == 'all'
Requires-Dist: brunette ; extra == 'all'
Requires-Dist: codecov ; extra == 'all'
Requires-Dist: coverage ; extra == 'all'
Requires-Dist: pytest ; extra == 'all'
Requires-Dist: pytest-cov ; extra == 'all'
Requires-Dist: pytest-subprocess ; extra == 'all'
Requires-Dist: xdoctest ; extra == 'all'
Provides-Extra: build
Requires-Dist: cmake ; extra == 'build'
Requires-Dist: ninja ; extra == 'build'
Requires-Dist: scikit-build ; extra == 'build'
Requires-Dist: setuptools ; extra == 'build'
Requires-Dist: setuptools-scm[toml] ; extra == 'build'
Requires-Dist: wheel ; extra == 'build'
Provides-Extra: runtime
Requires-Dist: matplotlib ; extra == 'runtime'
Requires-Dist: networkx ; extra == 'runtime'
Requires-Dist: numpy ; extra == 'runtime'
Requires-Dist: scipy ; extra == 'runtime'
Requires-Dist: Sphinx ; extra == 'runtime'
Requires-Dist: sphinx-rtd-theme ; extra == 'runtime'
Requires-Dist: wbia-utool ; extra == 'runtime'
Requires-Dist: wildbook-ia ; extra == 'runtime'
Provides-Extra: tests
Requires-Dist: brunette ; extra == 'tests'
Requires-Dist: codecov ; extra == 'tests'
Requires-Dist: coverage ; extra == 'tests'
Requires-Dist: pytest ; extra == 'tests'
Requires-Dist: pytest-cov ; extra == 'tests'
Requires-Dist: pytest-subprocess ; extra == 'tests'
Requires-Dist: xdoctest ; extra == 'tests'
